{"packages":{"ohmybrew/laravel-shopify":{"dev-analysis-8nwRxg":{"name":"ohmybrew/laravel-shopify","description":"Shopify package for Laravel to aide in app development","keywords":["api","shopify","laravel","shopify-api"],"homepage":"","version":"dev-analysis-8nwRxg","version_normalized":"dev-analysis-8nwRxg","license":["MIT"],"authors":[{"name":"Tyler King","email":"tyler.n.king@gmail.com"}],"source":{"type":"git","url":"https://github.com/ohmybrew/laravel-shopify.git","reference":"7b0d0d57ff3b494d8577b90c6ad2219c72f3ced0"},"dist":{"type":"zip","url":"https://api.github.com/repos/ohmybrew/laravel-shopify/zipball/7b0d0d57ff3b494d8577b90c6ad2219c72f3ced0","reference":"7b0d0d57ff3b494d8577b90c6ad2219c72f3ced0","shasum":""},"type":"library","time":"2019-01-04T04:42:40+00:00","autoload":{"psr-4":{"OhMyBrew\\ShopifyApp\\":"src/ShopifyApp"}},"extra":{"laravel":{"providers":["OhMyBrew\\ShopifyApp\\ShopifyAppProvider"],"aliases":{"ShopifyApp":"OhMyBrew\\ShopifyApp\\Facades\\ShopifyApp"}}},"require":{"doctrine/dbal":"~2.5","laravel/framework":"~5.6","ohmybrew/basic-shopify-api":"~4.0","php":">=7.1.0"},"require-dev":{"orchestra/database":"~3.5","orchestra/testbench":"~3.5","phpunit/phpunit":"~6.0||~7.0","squizlabs/php_codesniffer":"^3.0","mockery/mockery":"^1.0"},"uid":2668670},"dev-master":{"name":"ohmybrew/laravel-shopify","description":"Shopify package for Laravel to aide in app development","keywords":["api","shopify","laravel","shopify-api"],"homepage":"","version":"dev-master","version_normalized":"9999999-dev","license":["MIT"],"authors":[{"name":"Tyler King","email":"tyler.n.king@gmail.com"}],"source":{"type":"git","url":"https://github.com/ohmybrew/laravel-shopify.git","reference":"3cd65e12cba206ac996cafd70f48ca4a2bb731d3"},"dist":{"type":"zip","url":"https://api.github.com/repos/ohmybrew/laravel-shopify/zipball/3cd65e12cba206ac996cafd70f48ca4a2bb731d3","reference":"3cd65e12cba206ac996cafd70f48ca4a2bb731d3","shasum":""},"type":"library","time":"2019-01-10T15:40:23+00:00","autoload":{"psr-4":{"OhMyBrew\\ShopifyApp\\":"src/ShopifyApp"}},"extra":{"laravel":{"providers":["OhMyBrew\\ShopifyApp\\ShopifyAppProvider"],"aliases":{"ShopifyApp":"OhMyBrew\\ShopifyApp\\Facades\\ShopifyApp"}}},"require":{"doctrine/dbal":"~2.5","laravel/framework":"~5.6","ohmybrew/basic-shopify-api":"~4.0","php":">=7.1.0"},"require-dev":{"squizlabs/php_codesniffer":"^3.0","orchestra/database":"~3.5","orchestra/testbench":"~3.5","phpunit/phpunit":"~6.0||~7.0","mockery/mockery":"^1.0"},"uid":1495174},"v0.1.0":{"name":"ohmybrew/laravel-shopify","description":"Shopify package for Laravel to aide in app development","keywords":["api","shopify","laravel","shopify-api"],"homepage":"","version":"v0.1.0","version_normalized":"0.1.0.0","license":["MIT"],"authors":[{"name":"Tyler King","email":"tyler.n.king@gmail.com"}],"source":{"type":"git","url":"https://github.com/ohmybrew/laravel-shopify.git","reference":"0dc70942d2ced96710861066cdf32d0dac2c285e"},"dist":{"type":"zip","url":"https://api.github.com/repos/ohmybrew/laravel-shopify/zipball/0dc70942d2ced96710861066cdf32d0dac2c285e","reference":"0dc70942d2ced96710861066cdf32d0dac2c285e","shasum":""},"type":"library","time":"2017-07-11T18:59:08+00:00","autoload":{"psr-4":{"OhMyBrew\\ShopifyApp\\":"src/ShopifyApp"}},"extra":{"laravel":{"providers":["OhMyBrew\\ShopifyApp\\ShopifyAppProvider"]}},"require":{"doctrine/dbal":"^2.5","laravel/framework":"5.4.*","ohmybrew/basic-shopify-api":"1.0.*","php":">=7.0.0"},"require-dev":{"orchestra/database":"~3.1","orchestra/testbench":"~3.0","phpunit/phpunit":"~5.7","satooshi/php-coveralls":"~1.0","squizlabs/php_codesniffer":"^3.0"},"uid":1495173},"v0.1.1":{"name":"ohmybrew/laravel-shopify","description":"Shopify package for Laravel to aide in app development","keywords":["api","shopify","laravel","shopify-api"],"homepage":"","version":"v0.1.1","version_normalized":"0.1.1.0","license":["MIT"],"authors":[{"name":"Tyler King","email":"tyler.n.king@gmail.com"}],"source":{"type":"git","url":"https://github.com/ohmybrew/laravel-shopify.git","reference":"4853956339c7ffccfd309b1c68efc5d628bd34e2"},"dist":{"type":"zip","url":"https://api.github.com/repos/ohmybrew/laravel-shopify/zipball/4853956339c7ffccfd309b1c68efc5d628bd34e2","reference":"4853956339c7ffccfd309b1c68efc5d628bd34e2","shasum":""},"type":"library","time":"2017-07-12T05:17:11+00:00","autoload":{"psr-4":{"OhMyBrew\\ShopifyApp\\":"src/ShopifyApp"}},"extra":{"laravel":{"providers":["OhMyBrew\\ShopifyApp\\ShopifyAppProvider"]}},"require":{"doctrine/dbal":"^2.5","laravel/framework":"5.4.*","ohmybrew/basic-shopify-api":"1.0.*","php":">=7.0.0"},"require-dev":{"orchestra/database":"~3.1","orchestra/testbench":"~3.0","phpunit/phpunit":"~5.7","satooshi/php-coveralls":"~1.0","squizlabs/php_codesniffer":"^3.0"},"uid":1495185},"v1.0.0":{"name":"ohmybrew/laravel-shopify","description":"Shopify package for Laravel to aide in app development","keywords":["api","shopify","laravel","shopify-api"],"homepage":"","version":"v1.0.0","version_normalized":"1.0.0.0","license":["MIT"],"authors":[{"name":"Tyler King","email":"tyler.n.king@gmail.com"}],"source":{"type":"git","url":"https://github.com/ohmybrew/laravel-shopify.git","reference":"b20bebba2063e5c37c9839de25d12362d1dddcee"},"dist":{"type":"zip","url":"https://api.github.com/repos/ohmybrew/laravel-shopify/zipball/b20bebba2063e5c37c9839de25d12362d1dddcee","reference":"b20bebba2063e5c37c9839de25d12362d1dddcee","shasum":""},"type":"library","time":"2017-07-21T13:48:20+00:00","autoload":{"psr-4":{"OhMyBrew\\ShopifyApp\\":"src/ShopifyApp"}},"extra":{"laravel":{"providers":["OhMyBrew\\ShopifyApp\\ShopifyAppProvider"]}},"require":{"doctrine/dbal":"^2.5","laravel/framework":"5.4.*","ohmybrew/basic-shopify-api":"1.0.*","php":">=7.0.0"},"require-dev":{"orchestra/database":"~3.1","orchestra/testbench":"~3.0","phpunit/phpunit":"~5.7","satooshi/php-coveralls":"~1.0","squizlabs/php_codesniffer":"^3.0"},"uid":1512305},"v1.1.0":{"name":"ohmybrew/laravel-shopify","description":"Shopify package for Laravel to aide in app development","keywords":["api","shopify","laravel","shopify-api"],"homepage":"","version":"v1.1.0","version_normalized":"1.1.0.0","license":["MIT"],"authors":[{"name":"Tyler King","email":"tyler.n.king@gmail.com"}],"source":{"type":"git","url":"https://github.com/ohmybrew/laravel-shopify.git","reference":"c961f4e038e1b1fc4b42e0c90cfc089a0b631409"},"dist":{"type":"zip","url":"https://api.github.com/repos/ohmybrew/laravel-shopify/zipball/c961f4e038e1b1fc4b42e0c90cfc089a0b631409","reference":"c961f4e038e1b1fc4b42e0c90cfc089a0b631409","shasum":""},"type":"library","time":"2017-08-07T04:20:21+00:00","autoload":{"psr-4":{"OhMyBrew\\ShopifyApp\\":"src/ShopifyApp"}},"extra":{"laravel":{"providers":["OhMyBrew\\ShopifyApp\\ShopifyAppProvider"]}},"require":{"doctrine/dbal":"^2.5","laravel/framework":"5.4.*","ohmybrew/basic-shopify-api":"1.0.*","php":">=7.0.0"},"require-dev":{"orchestra/database":"~3.1","orchestra/testbench":"~3.0","phpunit/phpunit":"~5.7","satooshi/php-coveralls":"~1.0","squizlabs/php_codesniffer":"^3.0"},"uid":1540813},"v1.2.0":{"name":"ohmybrew/laravel-shopify","description":"Shopify package for Laravel to aide in app development","keywords":["api","shopify","laravel","shopify-api"],"homepage":"","version":"v1.2.0","version_normalized":"1.2.0.0","license":["MIT"],"authors":[{"name":"Tyler King","email":"tyler.n.king@gmail.com"}],"source":{"type":"git","url":"https://github.com/ohmybrew/laravel-shopify.git","reference":"2bd947a2bf8d1aa7ba382b04d7fafa95bc1ce36b"},"dist":{"type":"zip","url":"https://api.github.com/repos/ohmybrew/laravel-shopify/zipball/2bd947a2bf8d1aa7ba382b04d7fafa95bc1ce36b","reference":"2bd947a2bf8d1aa7ba382b04d7fafa95bc1ce36b","shasum":""},"type":"library","time":"2017-08-15T17:41:52+00:00","autoload":{"psr-4":{"OhMyBrew\\ShopifyApp\\":"src/ShopifyApp"}},"extra":{"laravel":{"providers":["OhMyBrew\\ShopifyApp\\ShopifyAppProvider"]}},"require":{"doctrine/dbal":"^2.5","laravel/framework":"5.4.*","ohmybrew/basic-shopify-api":"1.0.*","php":">=7.0.0"},"require-dev":{"orchestra/database":"~3.1","orchestra/testbench":"~3.0","phpunit/phpunit":"~5.7","satooshi/php-coveralls":"~1.0","squizlabs/php_codesniffer":"^3.0"},"uid":1556096},"v1.3.0":{"name":"ohmybrew/laravel-shopify","description":"Shopify package for Laravel to aide in app development","keywords":["api","shopify","laravel","shopify-api"],"homepage":"","version":"v1.3.0","version_normalized":"1.3.0.0","license":["MIT"],"authors":[{"name":"Tyler King","email":"tyler.n.king@gmail.com"}],"source":{"type":"git","url":"https://github.com/ohmybrew/laravel-shopify.git","reference":"f7908a553055282165d34df343dad2d546954239"},"dist":{"type":"zip","url":"https://api.github.com/repos/ohmybrew/laravel-shopify/zipball/f7908a553055282165d34df343dad2d546954239","reference":"f7908a553055282165d34df343dad2d546954239","shasum":""},"type":"library","time":"2017-08-30T14:59:33+00:00","autoload":{"psr-4":{"OhMyBrew\\ShopifyApp\\":"src/ShopifyApp"}},"require":{"doctrine/dbal":"~2.5.0","laravel/framework":"~5.5.0","ohmybrew/basic-shopify-api":"~1.0.0","php":">=7.0.0"},"require-dev":{"orchestra/database":"~3.5.0","orchestra/testbench":"~3.5.0","phpunit/phpunit":"~6.0","satooshi/php-coveralls":"~1.0","squizlabs/php_codesniffer":"^3.0"},"uid":1583055},"v1.3.1":{"name":"ohmybrew/laravel-shopify","description":"Shopify package for Laravel to aide in app development","keywords":["api","shopify","laravel","shopify-api"],"homepage":"","version":"v1.3.1","version_normalized":"1.3.1.0","license":["MIT"],"authors":[{"name":"Tyler King","email":"tyler.n.king@gmail.com"}],"source":{"type":"git","url":"https://github.com/ohmybrew/laravel-shopify.git","reference":"5e88ac66e2170a821c6b8f10180baec08b11d87e"},"dist":{"type":"zip","url":"https://api.github.com/repos/ohmybrew/laravel-shopify/zipball/5e88ac66e2170a821c6b8f10180baec08b11d87e","reference":"5e88ac66e2170a821c6b8f10180baec08b11d87e","shasum":""},"type":"library","time":"2017-11-06T16:52:06+00:00","autoload":{"psr-4":{"OhMyBrew\\ShopifyApp\\":"src/ShopifyApp"}},"require":{"doctrine/dbal":"~2.5.0","laravel/framework":"~5.5.0","ohmybrew/basic-shopify-api":"~1.0.0","php":">=7.0.0"},"require-dev":{"orchestra/database":"~3.5.0","orchestra/testbench":"~3.5.0","phpunit/phpunit":"~6.0","satooshi/php-coveralls":"~1.0","squizlabs/php_codesniffer":"^3.0"},"uid":1708402},"v2.0.0":{"name":"ohmybrew/laravel-shopify","description":"Shopify package for Laravel to aide in app development","keywords":["api","shopify","laravel","shopify-api"],"homepage":"","version":"v2.0.0","version_normalized":"2.0.0.0","license":["MIT"],"authors":[{"name":"Tyler King","email":"tyler.n.king@gmail.com"}],"source":{"type":"git","url":"https://github.com/ohmybrew/laravel-shopify.git","reference":"b1fa0aacff2c0091e649cf321e7b0dcbe774592c"},"dist":{"type":"zip","url":"https://api.github.com/repos/ohmybrew/laravel-shopify/zipball/b1fa0aacff2c0091e649cf321e7b0dcbe774592c","reference":"b1fa0aacff2c0091e649cf321e7b0dcbe774592c","shasum":""},"type":"library","time":"2018-01-25T17:59:22+00:00","autoload":{"psr-4":{"OhMyBrew\\ShopifyApp\\":"src/ShopifyApp"}},"require":{"doctrine/dbal":"~2.5.0","laravel/framework":"~5.5.0","ohmybrew/basic-shopify-api":"~1.0.0","php":">=7.0.0"},"require-dev":{"orchestra/database":"~3.5.0","orchestra/testbench":"~3.5.0","phpunit/phpunit":"~6.0","satooshi/php-coveralls":"~1.0","squizlabs/php_codesniffer":"^3.0"},"uid":1870340},"v2.0.1":{"name":"ohmybrew/laravel-shopify","description":"Shopify package for Laravel to aide in app development","keywords":["api","shopify","laravel","shopify-api"],"homepage":"","version":"v2.0.1","version_normalized":"2.0.1.0","license":["MIT"],"authors":[{"name":"Tyler King","email":"tyler.n.king@gmail.com"}],"source":{"type":"git","url":"https://github.com/ohmybrew/laravel-shopify.git","reference":"3f247370ca8418f6a92a10fc45688e6377e8a93e"},"dist":{"type":"zip","url":"https://api.github.com/repos/ohmybrew/laravel-shopify/zipball/3f247370ca8418f6a92a10fc45688e6377e8a93e","reference":"3f247370ca8418f6a92a10fc45688e6377e8a93e","shasum":""},"type":"library","time":"2018-02-12T17:55:30+00:00","autoload":{"psr-4":{"OhMyBrew\\ShopifyApp\\":"src/ShopifyApp"}},"require":{"doctrine/dbal":"~2.5.0","laravel/framework":"~5.5","ohmybrew/basic-shopify-api":"~1.0","php":">=7.0.0"},"require-dev":{"orchestra/database":"~3.5.0","orchestra/testbench":"~3.5.0","phpunit/phpunit":"~6.0","satooshi/php-coveralls":"~1.0","squizlabs/php_codesniffer":"^3.0"},"uid":1911012},"v2.1.0":{"name":"ohmybrew/laravel-shopify","description":"Shopify package for Laravel to aide in app development","keywords":["api","shopify","laravel","shopify-api"],"homepage":"","version":"v2.1.0","version_normalized":"2.1.0.0","license":["MIT"],"authors":[{"name":"Tyler King","email":"tyler.n.king@gmail.com"}],"source":{"type":"git","url":"https://github.com/ohmybrew/laravel-shopify.git","reference":"f6604c5bb83aa0ccf40b0c1855a7615f117fef35"},"dist":{"type":"zip","url":"https://api.github.com/repos/ohmybrew/laravel-shopify/zipball/f6604c5bb83aa0ccf40b0c1855a7615f117fef35","reference":"f6604c5bb83aa0ccf40b0c1855a7615f117fef35","shasum":""},"type":"library","time":"2018-03-11T16:53:55+00:00","autoload":{"psr-4":{"OhMyBrew\\ShopifyApp\\":"src/ShopifyApp"}},"require":{"doctrine/dbal":"~2.5.0","laravel/framework":"~5.5","ohmybrew/basic-shopify-api":"~1.0","php":">=7.0.0"},"require-dev":{"orchestra/database":"~3.5.0","orchestra/testbench":"~3.5.0","phpunit/phpunit":"~6.0","satooshi/php-coveralls":"~1.0","squizlabs/php_codesniffer":"^3.0"},"uid":1981162},"v2.1.1":{"name":"ohmybrew/laravel-shopify","description":"Shopify package for Laravel to aide in app development","keywords":["api","shopify","laravel","shopify-api"],"homepage":"","version":"v2.1.1","version_normalized":"2.1.1.0","license":["MIT"],"authors":[{"name":"Tyler King","email":"tyler.n.king@gmail.com"}],"source":{"type":"git","url":"https://github.com/ohmybrew/laravel-shopify.git","reference":"f996028a36c315dac9ab11f2fd6fce08b8878b50"},"dist":{"type":"zip","url":"https://api.github.com/repos/ohmybrew/laravel-shopify/zipball/f996028a36c315dac9ab11f2fd6fce08b8878b50","reference":"f996028a36c315dac9ab11f2fd6fce08b8878b50","shasum":""},"type":"library","time":"2018-03-19T16:28:06+00:00","autoload":{"psr-4":{"OhMyBrew\\ShopifyApp\\":"src/ShopifyApp"}},"require":{"doctrine/dbal":"~2.5.0","laravel/framework":"~5.5","ohmybrew/basic-shopify-api":"~1.0","php":">=7.0.0"},"require-dev":{"orchestra/database":"~3.5.0","orchestra/testbench":"~3.5.0","phpunit/phpunit":"~6.0","satooshi/php-coveralls":"~1.0","squizlabs/php_codesniffer":"^3.0"},"uid":2006458},"v2.2.0":{"name":"ohmybrew/laravel-shopify","description":"Shopify package for Laravel to aide in app development","keywords":["api","shopify","laravel","shopify-api"],"homepage":"","version":"v2.2.0","version_normalized":"2.2.0.0","license":["MIT"],"authors":[{"name":"Tyler King","email":"tyler.n.king@gmail.com"}],"source":{"type":"git","url":"https://github.com/ohmybrew/laravel-shopify.git","reference":"4e0ad00a8a849a81206d5fa4cd73480cb9135e31"},"dist":{"type":"zip","url":"https://api.github.com/repos/ohmybrew/laravel-shopify/zipball/4e0ad00a8a849a81206d5fa4cd73480cb9135e31","reference":"4e0ad00a8a849a81206d5fa4cd73480cb9135e31","shasum":""},"type":"library","time":"2018-04-25T16:52:49+00:00","autoload":{"psr-4":{"OhMyBrew\\ShopifyApp\\":"src/ShopifyApp"}},"require":{"doctrine/dbal":"~2.5.0","laravel/framework":"~5.5","ohmybrew/basic-shopify-api":"~1.0","php":">=7.0.0"},"require-dev":{"orchestra/database":"~3.5.0","orchestra/testbench":"~3.5.0","phpunit/phpunit":"~6.0","satooshi/php-coveralls":"~1.0","squizlabs/php_codesniffer":"^3.0"},"uid":2135291},"v2.3.0":{"name":"ohmybrew/laravel-shopify","description":"Shopify package for Laravel to aide in app development","keywords":["api","shopify","laravel","shopify-api"],"homepage":"","version":"v2.3.0","version_normalized":"2.3.0.0","license":["MIT"],"authors":[{"name":"Tyler King","email":"tyler.n.king@gmail.com"}],"source":{"type":"git","url":"https://github.com/ohmybrew/laravel-shopify.git","reference":"97239254a7c1895661ee30845f3aa6af3cab5ad9"},"dist":{"type":"zip","url":"https://api.github.com/repos/ohmybrew/laravel-shopify/zipball/97239254a7c1895661ee30845f3aa6af3cab5ad9","reference":"97239254a7c1895661ee30845f3aa6af3cab5ad9","shasum":""},"type":"library","time":"2018-05-23T02:26:28+00:00","autoload":{"psr-4":{"OhMyBrew\\ShopifyApp\\":"src/ShopifyApp"}},"require":{"doctrine/dbal":"~2.5.0","laravel/framework":"~5.5","ohmybrew/basic-shopify-api":"~3.0","php":">=7.0.0"},"require-dev":{"orchestra/database":"~3.5.0","orchestra/testbench":"~3.5.0","phpunit/phpunit":"~6.0","satooshi/php-coveralls":"~1.0","squizlabs/php_codesniffer":"^3.0"},"uid":2218084},"v2.3.1":{"name":"ohmybrew/laravel-shopify","description":"Shopify package for Laravel to aide in app development","keywords":["api","shopify","laravel","shopify-api"],"homepage":"","version":"v2.3.1","version_normalized":"2.3.1.0","license":["MIT"],"authors":[{"name":"Tyler King","email":"tyler.n.king@gmail.com"}],"source":{"type":"git","url":"https://github.com/ohmybrew/laravel-shopify.git","reference":"7acc855f777a35377fd29a73045e7d4536e7e0a7"},"dist":{"type":"zip","url":"https://api.github.com/repos/ohmybrew/laravel-shopify/zipball/7acc855f777a35377fd29a73045e7d4536e7e0a7","reference":"7acc855f777a35377fd29a73045e7d4536e7e0a7","shasum":""},"type":"library","time":"2018-05-30T01:25:06+00:00","autoload":{"psr-4":{"OhMyBrew\\ShopifyApp\\":"src/ShopifyApp"}},"require":{"doctrine/dbal":"~2.5","laravel/framework":"~5.5","ohmybrew/basic-shopify-api":"~3.0","php":">=7.0.0"},"require-dev":{"orchestra/database":"~3.5","orchestra/testbench":"~3.5","phpunit/phpunit":"~6.0||~7.0","squizlabs/php_codesniffer":"^3.0"},"uid":2230148},"v2.3.2":{"name":"ohmybrew/laravel-shopify","description":"Shopify package for Laravel to aide in app development","keywords":["api","shopify","laravel","shopify-api"],"homepage":"","version":"v2.3.2","version_normalized":"2.3.2.0","license":["MIT"],"authors":[{"name":"Tyler King","email":"tyler.n.king@gmail.com"}],"source":{"type":"git","url":"https://github.com/ohmybrew/laravel-shopify.git","reference":"af097801d03d4eecc4411b0ab5eaac9a8358f3b2"},"dist":{"type":"zip","url":"https://api.github.com/repos/ohmybrew/laravel-shopify/zipball/af097801d03d4eecc4411b0ab5eaac9a8358f3b2","reference":"af097801d03d4eecc4411b0ab5eaac9a8358f3b2","shasum":""},"type":"library","time":"2018-07-24T17:47:19+00:00","autoload":{"psr-4":{"OhMyBrew\\ShopifyApp\\":"src/ShopifyApp"}},"require":{"doctrine/dbal":"~2.5","laravel/framework":"~5.5","ohmybrew/basic-shopify-api":"~3.0","php":">=7.0.0"},"require-dev":{"orchestra/database":"~3.5","orchestra/testbench":"~3.5","phpunit/phpunit":"~6.0||~7.0","squizlabs/php_codesniffer":"^3.0"},"uid":2355403},"v3.0.0":{"name":"ohmybrew/laravel-shopify","description":"Shopify package for Laravel to aide in app development","keywords":["api","shopify","laravel","shopify-api"],"homepage":"","version":"v3.0.0","version_normalized":"3.0.0.0","license":["MIT"],"authors":[{"name":"Tyler King","email":"tyler.n.king@gmail.com"}],"source":{"type":"git","url":"https://github.com/ohmybrew/laravel-shopify.git","reference":"e55c3e80a17e958f296c823644d2573ee742c3da"},"dist":{"type":"zip","url":"https://api.github.com/repos/ohmybrew/laravel-shopify/zipball/e55c3e80a17e958f296c823644d2573ee742c3da","reference":"e55c3e80a17e958f296c823644d2573ee742c3da","shasum":""},"type":"library","time":"2018-07-20T02:21:32+00:00","autoload":{"psr-4":{"OhMyBrew\\ShopifyApp\\":"src/ShopifyApp"}},"require":{"doctrine/dbal":"~2.5","laravel/framework":"~5.5","ohmybrew/basic-shopify-api":"~3.0","php":">=7.1.0"},"require-dev":{"orchestra/database":"~3.5","orchestra/testbench":"~3.5","phpunit/phpunit":"~6.0||~7.0","squizlabs/php_codesniffer":"^3.0"},"uid":2345533},"v3.0.1":{"name":"ohmybrew/laravel-shopify","description":"Shopify package for Laravel to aide in app development","keywords":["api","shopify","laravel","shopify-api"],"homepage":"","version":"v3.0.1","version_normalized":"3.0.1.0","license":["MIT"],"authors":[{"name":"Tyler King","email":"tyler.n.king@gmail.com"}],"source":{"type":"git","url":"https://github.com/ohmybrew/laravel-shopify.git","reference":"51ba9dec7c400227308f4eb546d1f61e8d82eb04"},"dist":{"type":"zip","url":"https://api.github.com/repos/ohmybrew/laravel-shopify/zipball/51ba9dec7c400227308f4eb546d1f61e8d82eb04","reference":"51ba9dec7c400227308f4eb546d1f61e8d82eb04","shasum":""},"type":"library","time":"2018-07-24T17:38:30+00:00","autoload":{"psr-4":{"OhMyBrew\\ShopifyApp\\":"src/ShopifyApp"}},"require":{"doctrine/dbal":"~2.5","laravel/framework":"~5.5","ohmybrew/basic-shopify-api":"~3.0","php":">=7.1.0"},"require-dev":{"orchestra/database":"~3.5","orchestra/testbench":"~3.5","phpunit/phpunit":"~6.0||~7.0","squizlabs/php_codesniffer":"^3.0"},"uid":2355394},"v3.0.2":{"name":"ohmybrew/laravel-shopify","description":"Shopify package for Laravel to aide in app development","keywords":["api","shopify","laravel","shopify-api"],"homepage":"","version":"v3.0.2","version_normalized":"3.0.2.0","license":["MIT"],"authors":[{"name":"Tyler King","email":"tyler.n.king@gmail.com"}],"source":{"type":"git","url":"https://github.com/ohmybrew/laravel-shopify.git","reference":"f051ea114941a0c0e9913f33250df9f18ba43b0a"},"dist":{"type":"zip","url":"https://api.github.com/repos/ohmybrew/laravel-shopify/zipball/f051ea114941a0c0e9913f33250df9f18ba43b0a","reference":"f051ea114941a0c0e9913f33250df9f18ba43b0a","shasum":""},"type":"library","time":"2018-08-16T15:15:33+00:00","autoload":{"psr-4":{"OhMyBrew\\ShopifyApp\\":"src/ShopifyApp"}},"require":{"doctrine/dbal":"~2.5","laravel/framework":"~5.5","ohmybrew/basic-shopify-api":"~3.0","php":">=7.1.0"},"require-dev":{"orchestra/database":"~3.5","orchestra/testbench":"~3.5","phpunit/phpunit":"~6.0||~7.0","squizlabs/php_codesniffer":"^3.0"},"uid":2404347},"v3.1.0":{"name":"ohmybrew/laravel-shopify","description":"Shopify package for Laravel to aide in app development","keywords":["api","shopify","laravel","shopify-api"],"homepage":"","version":"v3.1.0","version_normalized":"3.1.0.0","license":["MIT"],"authors":[{"name":"Tyler King","email":"tyler.n.king@gmail.com"}],"source":{"type":"git","url":"https://github.com/ohmybrew/laravel-shopify.git","reference":"9fe82e292da39f90c1a1033f481058e673d7dac4"},"dist":{"type":"zip","url":"https://api.github.com/repos/ohmybrew/laravel-shopify/zipball/9fe82e292da39f90c1a1033f481058e673d7dac4","reference":"9fe82e292da39f90c1a1033f481058e673d7dac4","shasum":""},"type":"library","time":"2018-08-23T02:52:45+00:00","autoload":{"psr-4":{"OhMyBrew\\ShopifyApp\\":"src/ShopifyApp"}},"extra":{"laravel":{"providers":["OhMyBrew\\ShopifyApp\\ShopifyAppProvider"],"aliases":{"ShopifyApp":"OhMyBrew\\ShopifyApp\\Facades\\ShopifyApp"}}},"require":{"doctrine/dbal":"~2.5","laravel/framework":"~5.5","ohmybrew/basic-shopify-api":"~3.0","php":">=7.1.0"},"require-dev":{"orchestra/database":"~3.5","orchestra/testbench":"~3.5","phpunit/phpunit":"~6.0||~7.0","squizlabs/php_codesniffer":"^3.0"},"uid":2415205},"v3.1.1":{"name":"ohmybrew/laravel-shopify","description":"Shopify package for Laravel to aide in app development","keywords":["api","shopify","laravel","shopify-api"],"homepage":"","version":"v3.1.1","version_normalized":"3.1.1.0","license":["MIT"],"authors":[{"name":"Tyler King","email":"tyler.n.king@gmail.com"}],"source":{"type":"git","url":"https://github.com/ohmybrew/laravel-shopify.git","reference":"5aaa2d28d7432bff2fe487d02c8c47edfa5bee76"},"dist":{"type":"zip","url":"https://api.github.com/repos/ohmybrew/laravel-shopify/zipball/5aaa2d28d7432bff2fe487d02c8c47edfa5bee76","reference":"5aaa2d28d7432bff2fe487d02c8c47edfa5bee76","shasum":""},"type":"library","time":"2018-08-31T15:06:59+00:00","autoload":{"psr-4":{"OhMyBrew\\ShopifyApp\\":"src/ShopifyApp"}},"extra":{"laravel":{"providers":["OhMyBrew\\ShopifyApp\\ShopifyAppProvider"],"aliases":{"ShopifyApp":"OhMyBrew\\ShopifyApp\\Facades\\ShopifyApp"}}},"require":{"doctrine/dbal":"~2.5","laravel/framework":"~5.5","ohmybrew/basic-shopify-api":"~3.0","php":">=7.1.0"},"require-dev":{"orchestra/database":"~3.5","orchestra/testbench":"~3.5","phpunit/phpunit":"~6.0||~7.0","squizlabs/php_codesniffer":"^3.0"},"uid":2432947},"v3.2.0":{"name":"ohmybrew/laravel-shopify","description":"Shopify package for Laravel to aide in app development","keywords":["api","shopify","laravel","shopify-api"],"homepage":"","version":"v3.2.0","version_normalized":"3.2.0.0","license":["MIT"],"authors":[{"name":"Tyler King","email":"tyler.n.king@gmail.com"}],"source":{"type":"git","url":"https://github.com/ohmybrew/laravel-shopify.git","reference":"2572975bf3b38d4393d7200fbd1dc16053bf7efb"},"dist":{"type":"zip","url":"https://api.github.com/repos/ohmybrew/laravel-shopify/zipball/2572975bf3b38d4393d7200fbd1dc16053bf7efb","reference":"2572975bf3b38d4393d7200fbd1dc16053bf7efb","shasum":""},"type":"library","time":"2018-08-31T15:19:35+00:00","autoload":{"psr-4":{"OhMyBrew\\ShopifyApp\\":"src/ShopifyApp"}},"extra":{"laravel":{"providers":["OhMyBrew\\ShopifyApp\\ShopifyAppProvider"],"aliases":{"ShopifyApp":"OhMyBrew\\ShopifyApp\\Facades\\ShopifyApp"}}},"require":{"doctrine/dbal":"~2.5","laravel/framework":"~5.5","ohmybrew/basic-shopify-api":"~3.0","php":">=7.1.0"},"require-dev":{"orchestra/database":"~3.5","orchestra/testbench":"~3.5","phpunit/phpunit":"~6.0||~7.0","squizlabs/php_codesniffer":"^3.0","mockery/mockery":"^1.0"},"uid":2432984},"v4.0.0":{"name":"ohmybrew/laravel-shopify","description":"Shopify package for Laravel to aide in app development","keywords":["api","shopify","laravel","shopify-api"],"homepage":"","version":"v4.0.0","version_normalized":"4.0.0.0","license":["MIT"],"authors":[{"name":"Tyler King","email":"tyler.n.king@gmail.com"}],"source":{"type":"git","url":"https://github.com/ohmybrew/laravel-shopify.git","reference":"389e8b440f08f88fd09ce3c3170a95697a868b82"},"dist":{"type":"zip","url":"https://api.github.com/repos/ohmybrew/laravel-shopify/zipball/389e8b440f08f88fd09ce3c3170a95697a868b82","reference":"389e8b440f08f88fd09ce3c3170a95697a868b82","shasum":""},"type":"library","time":"2018-09-14T13:47:02+00:00","autoload":{"psr-4":{"OhMyBrew\\ShopifyApp\\":"src/ShopifyApp"}},"extra":{"laravel":{"providers":["OhMyBrew\\ShopifyApp\\ShopifyAppProvider"],"aliases":{"ShopifyApp":"OhMyBrew\\ShopifyApp\\Facades\\ShopifyApp"}}},"require":{"doctrine/dbal":"~2.5","laravel/framework":"~5.5","ohmybrew/basic-shopify-api":"~3.0","php":">=7.1.0"},"require-dev":{"orchestra/database":"~3.5","orchestra/testbench":"~3.5","phpunit/phpunit":"~6.0||~7.0","squizlabs/php_codesniffer":"^3.0","mockery/mockery":"^1.0"},"uid":2463874},"v4.0.1":{"name":"ohmybrew/laravel-shopify","description":"Shopify package for Laravel to aide in app development","keywords":["api","shopify","laravel","shopify-api"],"homepage":"","version":"v4.0.1","version_normalized":"4.0.1.0","license":["MIT"],"authors":[{"name":"Tyler King","email":"tyler.n.king@gmail.com"}],"source":{"type":"git","url":"https://github.com/ohmybrew/laravel-shopify.git","reference":"5b3d0f2f0a83ac104cda4e02620f946b64619fc5"},"dist":{"type":"zip","url":"https://api.github.com/repos/ohmybrew/laravel-shopify/zipball/5b3d0f2f0a83ac104cda4e02620f946b64619fc5","reference":"5b3d0f2f0a83ac104cda4e02620f946b64619fc5","shasum":""},"type":"library","time":"2018-09-17T12:05:41+00:00","autoload":{"psr-4":{"OhMyBrew\\ShopifyApp\\":"src/ShopifyApp"}},"extra":{"laravel":{"providers":["OhMyBrew\\ShopifyApp\\ShopifyAppProvider"],"aliases":{"ShopifyApp":"OhMyBrew\\ShopifyApp\\Facades\\ShopifyApp"}}},"require":{"doctrine/dbal":"~2.5","laravel/framework":"~5.5","ohmybrew/basic-shopify-api":"~3.0","php":">=7.1.0"},"require-dev":{"orchestra/database":"~3.5","orchestra/testbench":"~3.5","phpunit/phpunit":"~6.0||~7.0","squizlabs/php_codesniffer":"^3.0","mockery/mockery":"^1.0"},"uid":2467503},"v4.0.2":{"name":"ohmybrew/laravel-shopify","description":"Shopify package for Laravel to aide in app development","keywords":["api","shopify","laravel","shopify-api"],"homepage":"","version":"v4.0.2","version_normalized":"4.0.2.0","license":["MIT"],"authors":[{"name":"Tyler King","email":"tyler.n.king@gmail.com"}],"source":{"type":"git","url":"https://github.com/ohmybrew/laravel-shopify.git","reference":"aed501b3003573c91742f4303ea8af9707234a5b"},"dist":{"type":"zip","url":"https://api.github.com/repos/ohmybrew/laravel-shopify/zipball/aed501b3003573c91742f4303ea8af9707234a5b","reference":"aed501b3003573c91742f4303ea8af9707234a5b","shasum":""},"type":"library","time":"2018-09-24T20:07:50+00:00","autoload":{"psr-4":{"OhMyBrew\\ShopifyApp\\":"src/ShopifyApp"}},"extra":{"laravel":{"providers":["OhMyBrew\\ShopifyApp\\ShopifyAppProvider"],"aliases":{"ShopifyApp":"OhMyBrew\\ShopifyApp\\Facades\\ShopifyApp"}}},"require":{"doctrine/dbal":"~2.5","laravel/framework":"~5.5","ohmybrew/basic-shopify-api":"~3.0","php":">=7.1.0"},"require-dev":{"orchestra/database":"~3.5","orchestra/testbench":"~3.5","phpunit/phpunit":"~6.0||~7.0","squizlabs/php_codesniffer":"^3.0","mockery/mockery":"^1.0"},"uid":2481718},"v4.0.3":{"name":"ohmybrew/laravel-shopify","description":"Shopify package for Laravel to aide in app development","keywords":["api","shopify","laravel","shopify-api"],"homepage":"","version":"v4.0.3","version_normalized":"4.0.3.0","license":["MIT"],"authors":[{"name":"Tyler King","email":"tyler.n.king@gmail.com"}],"source":{"type":"git","url":"https://github.com/ohmybrew/laravel-shopify.git","reference":"05a69314605607c603ac45ee695979c636b38c2d"},"dist":{"type":"zip","url":"https://api.github.com/repos/ohmybrew/laravel-shopify/zipball/05a69314605607c603ac45ee695979c636b38c2d","reference":"05a69314605607c603ac45ee695979c636b38c2d","shasum":""},"type":"library","time":"2018-10-05T17:52:40+00:00","autoload":{"psr-4":{"OhMyBrew\\ShopifyApp\\":"src/ShopifyApp"}},"extra":{"laravel":{"providers":["OhMyBrew\\ShopifyApp\\ShopifyAppProvider"],"aliases":{"ShopifyApp":"OhMyBrew\\ShopifyApp\\Facades\\ShopifyApp"}}},"require":{"doctrine/dbal":"~2.5","laravel/framework":"~5.5","ohmybrew/basic-shopify-api":"~3.0","php":">=7.1.0"},"require-dev":{"orchestra/database":"~3.5","orchestra/testbench":"~3.5","phpunit/phpunit":"~6.0||~7.0","squizlabs/php_codesniffer":"^3.0","mockery/mockery":"^1.0"},"uid":2506358},"v4.0.4":{"name":"ohmybrew/laravel-shopify","description":"Shopify package for Laravel to aide in app development","keywords":["api","shopify","laravel","shopify-api"],"homepage":"","version":"v4.0.4","version_normalized":"4.0.4.0","license":["MIT"],"authors":[{"name":"Tyler King","email":"tyler.n.king@gmail.com"}],"source":{"type":"git","url":"https://github.com/ohmybrew/laravel-shopify.git","reference":"71dfbda02c7e886b325ebb377b52fb02aac16c37"},"dist":{"type":"zip","url":"https://api.github.com/repos/ohmybrew/laravel-shopify/zipball/71dfbda02c7e886b325ebb377b52fb02aac16c37","reference":"71dfbda02c7e886b325ebb377b52fb02aac16c37","shasum":""},"type":"library","time":"2018-10-09T01:23:36+00:00","autoload":{"psr-4":{"OhMyBrew\\ShopifyApp\\":"src/ShopifyApp"}},"extra":{"laravel":{"providers":["OhMyBrew\\ShopifyApp\\ShopifyAppProvider"],"aliases":{"ShopifyApp":"OhMyBrew\\ShopifyApp\\Facades\\ShopifyApp"}}},"require":{"doctrine/dbal":"~2.5","laravel/framework":"~5.5","ohmybrew/basic-shopify-api":"~3.0","php":">=7.1.0"},"require-dev":{"orchestra/database":"~3.5","orchestra/testbench":"~3.5","phpunit/phpunit":"~6.0||~7.0","squizlabs/php_codesniffer":"^3.0","mockery/mockery":"^1.0"},"uid":2511030},"v4.0.5":{"name":"ohmybrew/laravel-shopify","description":"Shopify package for Laravel to aide in app development","keywords":["api","shopify","laravel","shopify-api"],"homepage":"","version":"v4.0.5","version_normalized":"4.0.5.0","license":["MIT"],"authors":[{"name":"Tyler King","email":"tyler.n.king@gmail.com"}],"source":{"type":"git","url":"https://github.com/ohmybrew/laravel-shopify.git","reference":"01435c8d2c685254f4e42e4a959aa82f237b481b"},"dist":{"type":"zip","url":"https://api.github.com/repos/ohmybrew/laravel-shopify/zipball/01435c8d2c685254f4e42e4a959aa82f237b481b","reference":"01435c8d2c685254f4e42e4a959aa82f237b481b","shasum":""},"type":"library","time":"2018-10-09T19:36:32+00:00","autoload":{"psr-4":{"OhMyBrew\\ShopifyApp\\":"src/ShopifyApp"}},"extra":{"laravel":{"providers":["OhMyBrew\\ShopifyApp\\ShopifyAppProvider"],"aliases":{"ShopifyApp":"OhMyBrew\\ShopifyApp\\Facades\\ShopifyApp"}}},"require":{"doctrine/dbal":"~2.5","laravel/framework":"~5.5","ohmybrew/basic-shopify-api":"~3.0","php":">=7.1.0"},"require-dev":{"orchestra/database":"~3.5","orchestra/testbench":"~3.5","phpunit/phpunit":"~6.0||~7.0","squizlabs/php_codesniffer":"^3.0","mockery/mockery":"^1.0"},"uid":2517676},"v4.0.6":{"name":"ohmybrew/laravel-shopify","description":"Shopify package for Laravel to aide in app development","keywords":["api","shopify","laravel","shopify-api"],"homepage":"","version":"v4.0.6","version_normalized":"4.0.6.0","license":["MIT"],"authors":[{"name":"Tyler King","email":"tyler.n.king@gmail.com"}],"source":{"type":"git","url":"https://github.com/ohmybrew/laravel-shopify.git","reference":"98d5c6f4328bb7dd86525dbef94f185eefead68f"},"dist":{"type":"zip","url":"https://api.github.com/repos/ohmybrew/laravel-shopify/zipball/98d5c6f4328bb7dd86525dbef94f185eefead68f","reference":"98d5c6f4328bb7dd86525dbef94f185eefead68f","shasum":""},"type":"library","time":"2018-10-18T14:09:20+00:00","autoload":{"psr-4":{"OhMyBrew\\ShopifyApp\\":"src/ShopifyApp"}},"extra":{"laravel":{"providers":["OhMyBrew\\ShopifyApp\\ShopifyAppProvider"],"aliases":{"ShopifyApp":"OhMyBrew\\ShopifyApp\\Facades\\ShopifyApp"}}},"require":{"doctrine/dbal":"~2.5","laravel/framework":"~5.5","ohmybrew/basic-shopify-api":"~3.0","php":">=7.1.0"},"require-dev":{"orchestra/database":"~3.5","orchestra/testbench":"~3.5","phpunit/phpunit":"~6.0||~7.0","squizlabs/php_codesniffer":"^3.0","mockery/mockery":"^1.0"},"uid":2530083},"v4.1.0":{"name":"ohmybrew/laravel-shopify","description":"Shopify package for Laravel to aide in app development","keywords":["api","shopify","laravel","shopify-api"],"homepage":"","version":"v4.1.0","version_normalized":"4.1.0.0","license":["MIT"],"authors":[{"name":"Tyler King","email":"tyler.n.king@gmail.com"}],"source":{"type":"git","url":"https://github.com/ohmybrew/laravel-shopify.git","reference":"04403bbad82c01ce7fae42b4e51a0fc871a59eb1"},"dist":{"type":"zip","url":"https://api.github.com/repos/ohmybrew/laravel-shopify/zipball/04403bbad82c01ce7fae42b4e51a0fc871a59eb1","reference":"04403bbad82c01ce7fae42b4e51a0fc871a59eb1","shasum":""},"type":"library","time":"2018-11-02T03:06:38+00:00","autoload":{"psr-4":{"OhMyBrew\\ShopifyApp\\":"src/ShopifyApp"}},"extra":{"laravel":{"providers":["OhMyBrew\\ShopifyApp\\ShopifyAppProvider"],"aliases":{"ShopifyApp":"OhMyBrew\\ShopifyApp\\Facades\\ShopifyApp"}}},"require":{"doctrine/dbal":"~2.5","laravel/framework":"~5.5","ohmybrew/basic-shopify-api":"~4.0","php":">=7.1.0"},"require-dev":{"orchestra/database":"~3.5","orchestra/testbench":"~3.5","phpunit/phpunit":"~6.0||~7.0","squizlabs/php_codesniffer":"^3.0","mockery/mockery":"^1.0"},"uid":2555956},"v4.2.0":{"name":"ohmybrew/laravel-shopify","description":"Shopify package for Laravel to aide in app development","keywords":["api","shopify","laravel","shopify-api"],"homepage":"","version":"v4.2.0","version_normalized":"4.2.0.0","license":["MIT"],"authors":[{"name":"Tyler King","email":"tyler.n.king@gmail.com"}],"source":{"type":"git","url":"https://github.com/ohmybrew/laravel-shopify.git","reference":"72b796390c03729c0734e30a4012abe293e580da"},"dist":{"type":"zip","url":"https://api.github.com/repos/ohmybrew/laravel-shopify/zipball/72b796390c03729c0734e30a4012abe293e580da","reference":"72b796390c03729c0734e30a4012abe293e580da","shasum":""},"type":"library","time":"2018-11-15T02:33:48+00:00","autoload":{"psr-4":{"OhMyBrew\\ShopifyApp\\":"src/ShopifyApp"}},"extra":{"laravel":{"providers":["OhMyBrew\\ShopifyApp\\ShopifyAppProvider"],"aliases":{"ShopifyApp":"OhMyBrew\\ShopifyApp\\Facades\\ShopifyApp"}}},"require":{"doctrine/dbal":"~2.5","laravel/framework":"~5.5","ohmybrew/basic-shopify-api":"~4.0","php":">=7.1.0"},"require-dev":{"orchestra/database":"~3.5","orchestra/testbench":"~3.5","phpunit/phpunit":"~6.0||~7.0","squizlabs/php_codesniffer":"^3.0","mockery/mockery":"^1.0"},"uid":2581205},"v4.2.1":{"name":"ohmybrew/laravel-shopify","description":"Shopify package for Laravel to aide in app development","keywords":["api","shopify","laravel","shopify-api"],"homepage":"","version":"v4.2.1","version_normalized":"4.2.1.0","license":["MIT"],"authors":[{"name":"Tyler King","email":"tyler.n.king@gmail.com"}],"source":{"type":"git","url":"https://github.com/ohmybrew/laravel-shopify.git","reference":"cfa8ae061de96567cbec0bb5d7d2103685d959b0"},"dist":{"type":"zip","url":"https://api.github.com/repos/ohmybrew/laravel-shopify/zipball/cfa8ae061de96567cbec0bb5d7d2103685d959b0","reference":"cfa8ae061de96567cbec0bb5d7d2103685d959b0","shasum":""},"type":"library","time":"2018-11-22T04:13:29+00:00","autoload":{"psr-4":{"OhMyBrew\\ShopifyApp\\":"src/ShopifyApp"}},"extra":{"laravel":{"providers":["OhMyBrew\\ShopifyApp\\ShopifyAppProvider"],"aliases":{"ShopifyApp":"OhMyBrew\\ShopifyApp\\Facades\\ShopifyApp"}}},"require":{"doctrine/dbal":"~2.5","laravel/framework":"~5.5","ohmybrew/basic-shopify-api":"~4.0","php":">=7.1.0"},"require-dev":{"orchestra/database":"~3.5","orchestra/testbench":"~3.5","phpunit/phpunit":"~6.0||~7.0","squizlabs/php_codesniffer":"^3.0","mockery/mockery":"^1.0"},"uid":2594077},"v4.3.0":{"name":"ohmybrew/laravel-shopify","description":"Shopify package for Laravel to aide in app development","keywords":["api","shopify","laravel","shopify-api"],"homepage":"","version":"v4.3.0","version_normalized":"4.3.0.0","license":["MIT"],"authors":[{"name":"Tyler King","email":"tyler.n.king@gmail.com"}],"source":{"type":"git","url":"https://github.com/ohmybrew/laravel-shopify.git","reference":"18c8a9f2b12c6afa282d8c033d4dae445c99d5bf"},"dist":{"type":"zip","url":"https://api.github.com/repos/ohmybrew/laravel-shopify/zipball/18c8a9f2b12c6afa282d8c033d4dae445c99d5bf","reference":"18c8a9f2b12c6afa282d8c033d4dae445c99d5bf","shasum":""},"type":"library","time":"2018-12-08T16:59:58+00:00","autoload":{"psr-4":{"OhMyBrew\\ShopifyApp\\":"src/ShopifyApp"}},"extra":{"laravel":{"providers":["OhMyBrew\\ShopifyApp\\ShopifyAppProvider"],"aliases":{"ShopifyApp":"OhMyBrew\\ShopifyApp\\Facades\\ShopifyApp"}}},"require":{"doctrine/dbal":"~2.5","laravel/framework":"~5.5","ohmybrew/basic-shopify-api":"~4.0","php":">=7.1.0"},"require-dev":{"orchestra/database":"~3.5","orchestra/testbench":"~3.5","phpunit/phpunit":"~6.0||~7.0","squizlabs/php_codesniffer":"^3.0","mockery/mockery":"^1.0"},"uid":2631232},"v5.0.0":{"name":"ohmybrew/laravel-shopify","description":"Shopify package for Laravel to aide in app development","keywords":["api","shopify","laravel","shopify-api"],"homepage":"","version":"v5.0.0","version_normalized":"5.0.0.0","license":["MIT"],"authors":[{"name":"Tyler King","email":"tyler.n.king@gmail.com"}],"source":{"type":"git","url":"https://github.com/ohmybrew/laravel-shopify.git","reference":"c303f2127e1072f0c4ee1483214b926e9c83139c"},"dist":{"type":"zip","url":"https://api.github.com/repos/ohmybrew/laravel-shopify/zipball/c303f2127e1072f0c4ee1483214b926e9c83139c","reference":"c303f2127e1072f0c4ee1483214b926e9c83139c","shasum":""},"type":"library","time":"2018-12-20T14:38:59+00:00","autoload":{"psr-4":{"OhMyBrew\\ShopifyApp\\":"src/ShopifyApp"}},"extra":{"laravel":{"providers":["OhMyBrew\\ShopifyApp\\ShopifyAppProvider"],"aliases":{"ShopifyApp":"OhMyBrew\\ShopifyApp\\Facades\\ShopifyApp"}}},"require":{"doctrine/dbal":"~2.5","laravel/framework":"~5.6","ohmybrew/basic-shopify-api":"~4.0","php":">=7.1.0"},"require-dev":{"orchestra/database":"~3.5","orchestra/testbench":"~3.5","phpunit/phpunit":"~6.0||~7.0","squizlabs/php_codesniffer":"^3.0","mockery/mockery":"^1.0"},"uid":2650027},"v5.0.1":{"name":"ohmybrew/laravel-shopify","description":"Shopify package for Laravel to aide in app development","keywords":["api","shopify","laravel","shopify-api"],"homepage":"","version":"v5.0.1","version_normalized":"5.0.1.0","license":["MIT"],"authors":[{"name":"Tyler King","email":"tyler.n.king@gmail.com"}],"source":{"type":"git","url":"https://github.com/ohmybrew/laravel-shopify.git","reference":"772ce573c91348d9e4625eaeb9dd4251a3b1e3ac"},"dist":{"type":"zip","url":"https://api.github.com/repos/ohmybrew/laravel-shopify/zipball/772ce573c91348d9e4625eaeb9dd4251a3b1e3ac","reference":"772ce573c91348d9e4625eaeb9dd4251a3b1e3ac","shasum":""},"type":"library","time":"2018-12-20T21:52:20+00:00","autoload":{"psr-4":{"OhMyBrew\\ShopifyApp\\":"src/ShopifyApp"}},"extra":{"laravel":{"providers":["OhMyBrew\\ShopifyApp\\ShopifyAppProvider"],"aliases":{"ShopifyApp":"OhMyBrew\\ShopifyApp\\Facades\\ShopifyApp"}}},"require":{"doctrine/dbal":"~2.5","laravel/framework":"~5.6","ohmybrew/basic-shopify-api":"~4.0","php":">=7.1.0"},"require-dev":{"orchestra/database":"~3.5","orchestra/testbench":"~3.5","phpunit/phpunit":"~6.0||~7.0","squizlabs/php_codesniffer":"^3.0","mockery/mockery":"^1.0"},"uid":2650555},"v5.1.0":{"name":"ohmybrew/laravel-shopify","description":"Shopify package for Laravel to aide in app development","keywords":["api","shopify","laravel","shopify-api"],"homepage":"","version":"v5.1.0","version_normalized":"5.1.0.0","license":["MIT"],"authors":[{"name":"Tyler King","email":"tyler.n.king@gmail.com"}],"source":{"type":"git","url":"https://github.com/ohmybrew/laravel-shopify.git","reference":"d9eb61b79c4f264314b4263d49c9ae0543d53bb2"},"dist":{"type":"zip","url":"https://api.github.com/repos/ohmybrew/laravel-shopify/zipball/d9eb61b79c4f264314b4263d49c9ae0543d53bb2","reference":"d9eb61b79c4f264314b4263d49c9ae0543d53bb2","shasum":""},"type":"library","time":"2019-01-08T18:17:52+00:00","autoload":{"psr-4":{"OhMyBrew\\ShopifyApp\\":"src/ShopifyApp"}},"extra":{"laravel":{"providers":["OhMyBrew\\ShopifyApp\\ShopifyAppProvider"],"aliases":{"ShopifyApp":"OhMyBrew\\ShopifyApp\\Facades\\ShopifyApp"}}},"require":{"doctrine/dbal":"~2.5","laravel/framework":"~5.6","ohmybrew/basic-shopify-api":"~4.0","php":">=7.1.0"},"require-dev":{"orchestra/database":"~3.5","orchestra/testbench":"~3.5","phpunit/phpunit":"~6.0||~7.0","squizlabs/php_codesniffer":"^3.0","mockery/mockery":"^1.0"},"uid":2686412},"v5.1.1":{"name":"ohmybrew/laravel-shopify","description":"Shopify package for Laravel to aide in app development","keywords":["api","shopify","laravel","shopify-api"],"homepage":"","version":"v5.1.1","version_normalized":"5.1.1.0","license":["MIT"],"authors":[{"name":"Tyler King","email":"tyler.n.king@gmail.com"}],"source":{"type":"git","url":"https://github.com/ohmybrew/laravel-shopify.git","reference":"3cd65e12cba206ac996cafd70f48ca4a2bb731d3"},"dist":{"type":"zip","url":"https://api.github.com/repos/ohmybrew/laravel-shopify/zipball/3cd65e12cba206ac996cafd70f48ca4a2bb731d3","reference":"3cd65e12cba206ac996cafd70f48ca4a2bb731d3","shasum":""},"type":"library","time":"2019-01-10T15:40:23+00:00","autoload":{"psr-4":{"OhMyBrew\\ShopifyApp\\":"src/ShopifyApp"}},"extra":{"laravel":{"providers":["OhMyBrew\\ShopifyApp\\ShopifyAppProvider"],"aliases":{"ShopifyApp":"OhMyBrew\\ShopifyApp\\Facades\\ShopifyApp"}}},"require":{"doctrine/dbal":"~2.5","laravel/framework":"~5.6","ohmybrew/basic-shopify-api":"~4.0","php":">=7.1.0"},"require-dev":{"orchestra/database":"~3.5","orchestra/testbench":"~3.5","phpunit/phpunit":"~6.0||~7.0","squizlabs/php_codesniffer":"^3.0","mockery/mockery":"^1.0"},"uid":2686413}}}}